<?xml version="1.0" encoding="UTF-8"?>
<person><name>Maria van de Hee</name><gender>female</gender><color>0</color><event><type>Birth</type><date>15 Dec 1921</date><place>De Bilt, Utrecht, Netherlands</place><sources><source><footnote>Ancestry.com, Washington, Petitions for Naturalization, 1904-1991 (Ancestry.com Operations, Inc.), The National Archives at Seattle; Seattle, Washington; RG 21 United States District Courts; Volume: Petitions for Naturalization.</footnote></source></sources></event><event><type>Death</type><date>2 Jun 1994</date><place>Bothell, King, Washington, USA</place></event><event><type>Residence</type><place>Seattle, Washington, United States</place><sources><source><footnote>Ancestry.com, Washington, Petitions for Naturalization, 1904-1991 (Ancestry.com Operations, Inc.), The National Archives at Seattle; Seattle, Washington; RG 21 United States District Courts; Volume: Petitions for Naturalization.</footnote></source></sources></event><sources><source><footnote>Ancestry.com, Washington, Marriage Records, 1854-2013 (Ancestry.com Operations, Inc.).</footnote></source><source><footnote>Ancestry.com, Washington, Petitions for Naturalization, 1904-1991 (Ancestry.com Operations, Inc.), The National Archives at Seattle; Seattle, Washington; RG 21 United States District Courts; Volume: Petitions for Naturalization.</footnote></source></sources><parents id="30" rel="birth parents"><father>117</father><mother>135</mother><sibling id="115"/><sibling id="123"/><sibling id="118"/><currentchild>118</currentchild></parents></person>
