<?xml version="1.0" encoding="UTF-8"?>
<person><name>Janna Catharina van Mansom</name><gender>female</gender><color>0</color><currentspouse>30</currentspouse><currentparents>32</currentparents><event><type>Birth</type><date>9 Apr 1902</date><place>De Bilt, Utrecht, Netherlands</place></event><event><type>Death</type><date>4 Apr 1973</date><place>De Bilt</place></event><sources><source><footnote>Ancestry Family Trees (Online publication - Provo, UT, USA: Ancestry.com.  Original data:  Family Tree files submitted by Ancestry members.), Ancestry Family Tree.</footnote></source></sources><family id="30"><spouse>117</spouse><child id="120"/><child id="115"/><child id="123"/><child id="118"/><currentchild>118</currentchild><event><type>Marriage</type><date>28 Oct 1921</date><place>De Bilt, Utrecht, Netherlands</place></event></family><parents id="32" rel="birth parents"><father>126</father><mother>88</mother><sibling id="124"/><sibling id="130"/><sibling id="128"/><sibling id="131"/><sibling id="132"/><sibling id="129"/><sibling id="133"/><sibling id="137"/><sibling id="127"/><sibling id="125"/><sibling id="136"/><currentchild>135</currentchild></parents></person>
