<?xml version="1.0" encoding="UTF-8"?>
<person><name>William Andrew Geyer</name><gender>male</gender><color>0</color><event><type>Birth</type><date>10 Feb 1884</date><place>Bronson, Kansas, United States</place></event><event><type>Death</type><date>17 Jan 1949</date><place>Clarkston, Asotin, Washington, United States</place></event><event><type>Reference No</type><place>13 JAN 2017 12:01:07</place></event><family id="5"><spouse>38</spouse><child id="10"/><event><type>Reference No (Family)</type><place>13 JAN 2017 12:00:50</place></event></family><parents id="3" rel="birth parents"><father>12</father><mother>14</mother><sibling id="13"/><sibling id="11"/></parents></person>
