<?xml version="1.0" encoding="UTF-8"?>
<person><name>William St John</name><gender>male</gender><color>0</color><event><type>Birth</type><date>28 Jul 1883</date><place>Grayling, Crawford Michigan, USA</place><sources><source><footnote>Ancestry.com, Michigan, Death Records, 1867-1950 (Ancestry.com Operations, Inc.).</footnote></source><source><footnote>Ancestry.com, Michigan, Marriage Records, 1867-1952 (Ancestry.com Operations, Inc.).</footnote></source></sources></event><event><type>Death</type><date>22 Aug 1909</date><place>Grayling, Crawford Michigan, USA</place><sources><source><footnote>Ancestry.com, Michigan, Death Records, 1867-1950 (Ancestry.com Operations, Inc.).</footnote></source></sources></event><event><type>Residence</type><place>Grayling, Michigan</place><sources><source><footnote>Ancestry.com, Michigan, Marriage Records, 1867-1952 (Ancestry.com Operations, Inc.).</footnote></source></sources></event><sources><source><footnote>Ancestry.com, Washington, Marriage Records, 1854-2013 (Ancestry.com Operations, Inc.), Washington State Archives; Olympia, Washington; Marriage Register.</footnote></source><source><footnote>Ancestry.com, Michigan, Death Records, 1867-1950 (Ancestry.com Operations, Inc.).</footnote></source><source><footnote>Ancestry.com, Michigan, Marriage Records, 1867-1952 (Ancestry.com Operations, Inc.).</footnote></source><source><footnote>Ancestry Family Trees (Online publication - Provo, UT, USA: Ancestry.com.  Original data:  Family Tree files submitted by Ancestry members.), Ancestry Family Tree.</footnote></source></sources><parents id="15" rel="birth parents"><father>66</father><mother>76</mother><sibling id="67"/><sibling id="64"/><sibling id="68"/><sibling id="69"/><currentchild>69</currentchild></parents></person>
